Workbook

Sheet Instructions & Summary
A1: Glide Staff Tablet — Customer Launch Decision Questionnaire
A3: Purpose: collect the customer decisions required to finalize staff-tablet workflows, policies, permissions, and launch acceptance.
A5: How to complete 1. Open each category worksheet and enter one response per question in the yellow Customer Response column. 2. Add the customer decision owner and target response date. 3. Set Response Status to Under review, Answered, or Not applicable. 4. Use Notes / Follow-up for legal review, attachments, dependencies, or unresolved details. 5. If an answer is supplied in a separate approved document, enter the document title/version or URL in Customer Response.
A10: Category | B10: Purpose | C10: Affected Work | D10: Questions | E10: Answered | F10: Under Review | G10: Open | H10: Completion
A11: Launch payment, pricing, and receipt policy | B11: Define what customers pay, when they pay, how staff verify payment, and what proof is issued. | C11: Rental, return, payment, reconciliation | D11: 9 | E11: =COUNTIF('Payment & Pricing'!H6:H14,"Answered") | F11: =COUNTIF('Payment & Pricing'!H6:H14,"Under review") | G11: =COUNTIF('Payment & Pricing'!H6:H14,"Open") | H11: =IF(D11=0,0,E11/D11)
A12: PDPA, privacy, and rider identity | B12: Confirm the lawful, minimal customer information and notices required for rental operations. | C12: Rider registration and staff-assisted registration | D12: 10 | E12: =COUNTIF('PDPA & Identity'!H6:H15,"Answered") | F12: =COUNTIF('PDPA & Identity'!H6:H15,"Under review") | G12: =COUNTIF('PDPA & Identity'!H6:H15,"Open") | H12: =IF(D12=0,0,E12/D12)
A13: Tablet devices, offline operation, and device security | B13: Define the hardware and offline operating envelope that the standalone station app must support. | C13: App shell, authentication, bootstrap, sync | D13: 10 | E13: =COUNTIF('Tablet & Offline'!H6:H15,"Answered") | F13: =COUNTIF('Tablet & Offline'!H6:H15,"Under review") | G13: =COUNTIF('Tablet & Offline'!H6:H15,"Open") | H13: =IF(D13=0,0,E13/D13)
A14: Vehicle identification, returns, and inspection policy | B14: Define how bikes are identified, where they can be returned, and the safety checks that control availability. | C14: Rental start, return, bike checks | D14: 10 | E14: =COUNTIF('Vehicle & Inspection'!H6:H15,"Answered") | F14: =COUNTIF('Vehicle & Inspection'!H6:H15,"Under review") | G14: =COUNTIF('Vehicle & Inspection'!H6:H15,"Open") | H14: =IF(D14=0,0,E14/D14)
A15: Battery readiness and GPS/IoT policy | B15: Define the battery and connectivity conditions that allow or block rental at launch. | C15: Bike readiness and battery workflow | D15: 9 | E15: =COUNTIF('Battery & IoT'!H6:H14,"Answered") | F15: =COUNTIF('Battery & IoT'!H6:H14,"Under review") | G15: =COUNTIF('Battery & IoT'!H6:H14,"Open") | H15: =IF(D15=0,0,E15/D15)
A16: Roles, permissions, and high-risk approvals | B16: Define who may view, create, change, approve, export, and resolve operational records. | C16: Authorization, overrides, conflict resolution | D16: 10 | E16: =COUNTIF('Roles & Approvals'!H6:H15,"Answered") | F16: =COUNTIF('Roles & Approvals'!H6:H15,"Under review") | G16: =COUNTIF('Roles & Approvals'!H6:H15,"Open") | H16: =IF(D16=0,0,E16/D16)
A17: Backup mode and reconciliation | B17: Define when fallback operations begin and how temporary records safely enter the primary system. | C17: Backup export and reconciliation | D17: 11 | E17: =COUNTIF('Backup & Reconciliation'!H6:H16,"Answered") | F17: =COUNTIF('Backup & Reconciliation'!H6:H16,"Under review") | G17: =COUNTIF('Backup & Reconciliation'!H6:H16,"Open") | H17: =IF(D17=0,0,E17/D17)
A18: MVP acceptance and station demonstration | B18: Agree what must be demonstrated and signed off before station-assisted tablet rentals launch. | C18: Release gate | D18: 14 | E18: =COUNTIF('MVP Acceptance'!H6:H19,"Answered") | F18: =COUNTIF('MVP Acceptance'!H6:H19,"Under review") | G18: =COUNTIF('MVP Acceptance'!H6:H19,"Open") | H18: =IF(D18=0,0,E18/D18)
A21: Yellow cells require customer input. Green rows are answered. Red status cells remain open.

Sheet Payment & Pricing
A1: Launch payment, pricing, and receipt policy
A2: Define what customers pay, when they pay, how staff verify payment, and what proof is issued.
A3: Affected work: Rental, return, payment, reconciliation | Complete the yellow response cells and update the response status.
A5: Question ID | B5: Decision Question | C5: Why This Decision Is Required | D5: Response Guidance / Examples | E5: Customer Response | F5: Decision Owner | G5: Target Response Date | H5: Response Status | I5: Notes / Follow-up
A6: PAY-01 | B6: Which payment methods will be accepted at launch? | C6: The tablet and rider app need an exact list so they show only usable choices and capture the correct evidence. | D6: Select all approved methods, for example PromptPay/Thai QR, credit/debit card, digital wallet, cash, manual bank-transfer slip, prepaid wallet, or voucher. | H6: Open
A7: PAY-02 | B7: When is payment collected? | C7: The answer changes the rental and return workflow and determines whether a bike may be released with payment pending. | D7: Choose before rental, deposit before rental plus balance after return, full payment after return, or rules that vary by rider type. | H7: Open
A8: PAY-03 | B8: What is the launch pricing model? | C8: The system must calculate and display the expected charge consistently to riders and staff. | D8: Provide the base fee, per-minute/per-hour/day rate, included duration, packages, taxes, and any station-specific differences. | H8: Open
A9: PAY-04 | B9: Is a security deposit required? | C9: Deposit rules affect checkout eligibility, payment records, refunds, and customer support. | D9: State the amount, applicable rider types, payment method, release timing, and conditions for withholding part or all of it. | H9: Open
A10: PAY-05 | B10: What overtime or late-return rules apply? | C10: Riders need to understand additional charges before starting, and staff need a consistent calculation at return. | D10: Define the grace period, overtime rate, maximum charge, operating-hours handling, and escalation for an unreturned bike. | H10: Open
A11: PAY-06 | B11: What cancellation and refund rules apply? | C11: The customer and operations teams need an agreed process for failed starts, early cancellation, duplicate payment, service outage, and disputes. | D11: Describe eligible reasons, refund amount, approval role, required evidence, processing time, and how refunds are delivered. | H11: Open
A12: PAY-07 | B12: Who may verify or reject manual payment evidence? | C12: Manual slips cannot be treated as verified without an accountable reviewer and audit trail. | D12: Name the permitted roles, expected review time, evidence requirements, and whether a second approval is needed for corrections. | H12: Open
A13: PAY-08 | B13: What receipt or payment confirmation must be provided? | C13: The implementation needs to know which output formats and customer details are mandatory. | D13: Choose in-app, email, printed, downloadable PDF, or staff-shown confirmation; list required receipt fields and language requirements. | H13: Open
A14: PAY-09 | B14: How should payment disputes be handled? | C14: Disputes affect payment status, incident/support handling, and whether the rental can be closed. | D14: Specify the first contact, evidence reviewed, temporary status, decision authority, response SLA, and escalation path. | H14: Open

Sheet PDPA & Identity
A1: PDPA, privacy, and rider identity
A2: Confirm the lawful, minimal customer information and notices required for rental operations.
A3: Affected work: Rider registration and staff-assisted registration | Complete the yellow response cells and update the response status.
A5: Question ID | B5: Decision Question | C5: Why This Decision Is Required | D5: Response Guidance / Examples | E5: Customer Response | F5: Decision Owner | G5: Target Response Date | H5: Response Status | I5: Notes / Follow-up
A6: PDP-01 | B6: Who is the legal data controller for the service? | C6: The privacy notice must identify the responsible organization and provide a contact channel. | D6: Provide the legal entity name, address, privacy contact, email, phone, and data-protection contact if applicable. | H6: Open
A7: PDP-02 | B7: What final short PDPA notice should appear during registration? | C7: Riders need a concise notice at the point of collection before staff or the app records personal information. | D7: Provide approved Thai and English text or identify the legal reviewer responsible for supplying it. | H7: Open
A8: PDP-03 | B8: What full privacy notice should be linked or available by QR? | C8: The detailed notice must explain purposes, legal basis, retention, sharing, rights, and contact details. | D8: Provide the approved document/URL and version identifier for Thai and English notices. | H8: Open
A9: PDP-04 | B9: What personal information is required for Thai residents? | C9: The registration form should collect only information required for rental, safety, payment, support, and audit. | D9: Mark each field required or optional: name, phone, email, national ID reference, address, date of birth, emergency contact, and any other field. | H9: Open
A10: PDP-05 | B10: What personal information is required for tourists? | C10: Tourist identity and contact requirements may differ and must remain practical at a station. | D10: Mark each field required or optional: name, phone/WhatsApp, email, nationality, passport reference, accommodation, emergency contact, and any other field. | H10: Open
A11: PDP-06 | B11: How should ID or passport checks be performed? | C11: Uploading identity documents increases privacy and security obligations, so the minimum approved method must be explicit. | D11: Choose staff visual verification only, metadata/reference entry, partial-number storage, document image upload, or another approved method. | H11: Open
A12: PDP-07 | B12: How long is each type of personal and operational record retained? | C12: Retention periods are needed for deletion jobs, support, audit, evidence, and privacy notices. | D12: State periods for profiles, consent records, rentals, payments, identity references, incidents, evidence photos, audit logs, and backups. | H12: Open
A13: PDP-08 | B13: How can a customer exercise privacy rights or withdraw optional consent? | C13: The service needs a visible and workable request channel without blocking required rental records. | D13: Specify request channels, identity verification, responsible team, response time, and what happens to active or legally retained records. | H13: Open
A14: PDP-09 | B14: Is marketing or tourism-program consent included at launch? | C14: Optional purposes must remain separate from required rental terms and consent. | D14: Answer yes/no; if yes, provide separate wording, channels covered, withdrawal method, and proof requirements. | H14: Open
A15: PDP-10 | B15: Which organizations may receive customer data? | C15: Third-party sharing must be reflected in notices and system access controls. | D15: List payment providers, government bodies, support vendors, tourism partners, insurers, law enforcement conditions, and any cross-border processing. | H15: Open

Sheet Tablet & Offline
A1: Tablet devices, offline operation, and device security
A2: Define the hardware and offline operating envelope that the standalone station app must support.
A3: Affected work: App shell, authentication, bootstrap, sync | Complete the yellow response cells and update the response status.
A5: Question ID | B5: Decision Question | C5: Why This Decision Is Required | D5: Response Guidance / Examples | E5: Customer Response | F5: Decision Owner | G5: Target Response Date | H5: Response Status | I5: Notes / Follow-up
A6: TAB-01 | B6: Which tablet models and operating systems are approved? | C6: The app build, testing matrix, camera/file access, SQLite behavior, and device management depend on the target hardware. | D6: Provide manufacturer/model, OS and minimum version, screen size, memory/storage, camera requirement, and number of devices per station. | H6: Open
A7: TAB-02 | B7: Is landscape orientation required? | C7: The current wireframes are landscape-first, so the supported orientations must be agreed before high-fidelity UI and testing. | D7: Choose landscape only, portrait only, or both; note any mounting or kiosk constraints. | H7: Open
A8: TAB-03 | B8: How long may staff unlock and use the tablet offline? | C8: Cached authentication needs a time limit that balances service continuity and unauthorized-access risk. | D8: Specify the offline authentication TTL, whether it resets per shift, and who may grant an emergency extension. | H8: Open
A9: TAB-04 | B9: How long may operational records remain unsynced? | C9: The app needs warnings and escalation thresholds before local-only records create unacceptable operational or audit risk. | D9: Set warning, critical, and mandatory action thresholds, such as after 2 hours, shift end, or 24 hours. | H9: Open
A10: TAB-05 | B10: When is backup export mandatory? | C10: Staff need a clear trigger for moving from normal local queueing to the Google Workflow fallback. | D10: Define triggers based on outage duration, shift closeout, record count, station manager instruction, or backend failure type. | H10: Open
A11: TAB-06 | B11: How much local data and evidence must the device retain? | C11: Retention and storage limits affect disk usage, offline recovery, privacy, and evidence availability. | D11: State retention after sync, maximum evidence size/count, archive/deletion rules, and the minimum free-storage warning level. | H11: Open
A12: TAB-07 | B12: How are tablets assigned to stations and staff? | C12: Server authorization must know whether a device is fixed to one station or can move under manager control. | D12: Choose fixed station, multi-station pool, or manager reassignment; describe shift handoff and station-change approval. | H12: Open
A13: TAB-08 | B13: What happens when a tablet is lost, stolen, or damaged? | C13: The service needs a rapid way to stop access while preserving unsynced work when possible. | D13: Define who reports it, who disables it, expected response time, remote-wipe/MDM policy, replacement procedure, and unsynced-data recovery. | H13: Open
A14: TAB-09 | B14: What device security controls are required? | C14: Operational and personal data stored locally must be protected against casual or unauthorized access. | D14: Confirm PIN/biometric rules, auto-lock time, encryption, kiosk mode, MDM, screenshots, USB/file sharing, and app installation restrictions. | H14: Open
A15: TAB-10 | B15: How should device clock errors be handled? | C15: Offline records preserve device time, but major clock drift can make rentals and payments appear impossible. | D15: Set the warning tolerance, whether work may continue, who can correct the clock, and when manager review is mandatory. | H15: Open

Sheet Vehicle & Inspection
A1: Vehicle identification, returns, and inspection policy
A2: Define how bikes are identified, where they can be returned, and the safety checks that control availability.
A3: Affected work: Rental start, return, bike checks | Complete the yellow response cells and update the response status.
A5: Question ID | B5: Decision Question | C5: Why This Decision Is Required | D5: Response Guidance / Examples | E5: Customer Response | F5: Decision Owner | G5: Target Response Date | H5: Response Status | I5: Notes / Follow-up
A6: VEH-01 | B6: What is the official Vehicle ID format? | C6: A stable, human-readable identifier is required across bike labels, QR codes, rentals, evidence, maintenance, and reconciliation. | D6: Provide the format, example IDs, sequence owner, uniqueness rule, and whether existing manufacturer/asset numbers are retained. | H6: Open
A7: VEH-02 | B7: What information is encoded in the bike QR code? | C7: The customer and tablet scanners need a stable payload that does not expose sensitive or changeable data. | D7: Choose a Vehicle ID, deep link/URL, signed token, or another payload; specify versioning and replacement behavior. | H7: Open
A8: VEH-03 | B8: Where may customers return a bike? | C8: Return eligibility changes guidance, station capacity, charges, and exception handling. | D8: Choose origin station only, any launch station, designated return zones, or staff-approved storage-center handoff; describe exceptions. | H8: Open
A9: VEH-04 | B9: What are the final pre-use inspection items? | C9: Staff must know the exact checks required before a bike can be released. | D9: Confirm brakes, tires, lights, frame/handlebar/seat, battery, QR/ID, visible damage, accessories, and any FreeDare-specific checks. | H9: Open
A10: VEH-05 | B10: Which pre-use failures are critical rental blockers? | C10: The app must distinguish a note-worthy issue from an unsafe condition that prevents release. | D10: For each checklist item, define pass, minor issue, critical fail, allowed override, required evidence, and resulting bike status. | H10: Open
A11: VEH-06 | B11: What are the final return inspection items? | C11: Return inspection determines whether a bike becomes ready, remains pending, or enters maintenance/out-of-service. | D11: Confirm brakes, tires, lights, frame, battery, new damage, accessories, QR/ID, cleanliness, rider dispute, and any additional checks. | H11: Open
A12: VEH-07 | B12: Who may clear pending-inspection status? | C12: Returned bikes must not become rentable until an authorized person accepts the inspection result. | D12: Specify permitted roles, evidence requirements, and whether an ordinary pass can be cleared by station staff. | H12: Open
A13: VEH-08 | B13: Who may return a bike from maintenance or out-of-service to ready? | C13: A controlled quality check prevents unresolved safety issues from being overridden. | D13: Specify technician/manager roles, QC checklist, second approval if any, evidence, and audit note requirements. | H13: Open
A14: VEH-09 | B14: How should unreadable or replaced QR labels be handled? | C14: Staff need a safe fallback that avoids renting or updating the wrong bike. | D14: Define manual lookup, identity cross-check, temporary block, replacement authority, and audit/evidence requirements. | H14: Open
A15: VEH-10 | B15: What cleaning and preventive inspection schedule is mandatory? | C15: The tablet and admin system need due dates and escalation rules for routine fleet safety work. | D15: Confirm daily checks, seven-day cleaning, distance/monthly checks, responsible role, missed-task escalation, and required records. | H15: Open

Sheet Battery & IoT
A1: Battery readiness and GPS/IoT policy
A2: Define the battery and connectivity conditions that allow or block rental at launch.
A3: Affected work: Bike readiness and battery workflow | Complete the yellow response cells and update the response status.
A5: Question ID | B5: Decision Question | C5: Why This Decision Is Required | D5: Response Guidance / Examples | E5: Customer Response | F5: Decision Owner | G5: Target Response Date | H5: Response Status | I5: Notes / Follow-up
A6: BAT-01 | B6: What minimum battery charge allows a rental to start? | C6: The tablet needs a clear threshold to prevent avoidable breakdowns while keeping sufficient fleet available. | D6: Provide the percentage or status threshold, any trip/package exceptions, and who may override it. | H6: Open
A7: BAT-02 | B7: What battery conditions require immediate quarantine? | C7: Unsafe or abnormal batteries must be separated from bikes, charging, and customer service. | D7: Define temperature, swelling, leakage, odor, damage, error code, charging behavior, state-of-health, or staff-observed triggers. | H7: Open
A8: BAT-03 | B8: What battery states should appear at launch? | C8: Staff need consistent manual labels before reliable telemetry is available. | D8: Confirm states such as normal, low, charging, charged, abnormal, and quarantined, plus allowed transitions. | H8: Open
A9: BAT-04 | B9: Is each battery tracked with its own Battery ID? | C9: Separate IDs enable swap history, charging logs, quarantine, and lifecycle reporting. | D9: Answer yes/no; if yes, provide ID/QR format, labeling owner, and treatment of batteries fixed to a bike. | H9: Open
A10: BAT-05 | B10: What battery data is entered manually on day one? | C10: The MVP should not depend on IoT fields that are unavailable or unreliable. | D10: Choose charge level/status, swap, charge start/stop, charger/slot, abnormal flag, notes, photos, temperature, SOH, and cycle count. | H10: Open
A11: BAT-06 | B11: Does missing GPS or IoT connectivity block rental? | C11: The product must distinguish safety requirements from optional operational visibility. | D11: Choose hard blocker, warning only, blocker after a defined period, or station-manager decision; explain offline station behavior. | H11: Open
A12: BAT-07 | B12: Which GPS/IoT faults create an operational hold? | C12: Some device faults may indicate loss, tampering, lock failure, or inability to support the ride safely. | D12: List relevant fault codes/states, grace period, required staff check, override role, and resulting bike status. | H12: Open
A13: BAT-08 | B13: What charging and rotation procedure must staff follow? | C13: Manual operating rules are required before charger telemetry and optimization are stable. | D13: Describe charge start/stop records, timers, cabinet/slot assignment, rotation priority, supervision, and shift handoff. | H13: Open
A14: BAT-09 | B14: Who may release a quarantined battery back into service? | C14: A controlled decision prevents abnormal batteries from returning without inspection. | D14: Specify role, required tests, cooling/observation period, evidence, second approval, and disposal/escalation rules. | H14: Open

Sheet Roles & Approvals
A1: Roles, permissions, and high-risk approvals
A2: Define who may view, create, change, approve, export, and resolve operational records.
A3: Affected work: Authorization, overrides, conflict resolution | Complete the yellow response cells and update the response status.
A5: Question ID | B5: Decision Question | C5: Why This Decision Is Required | D5: Response Guidance / Examples | E5: Customer Response | F5: Decision Owner | G5: Target Response Date | H5: Response Status | I5: Notes / Follow-up
A6: ROL-01 | B6: Confirm the launch roles. | C6: Shared role names are needed for tablet, API, admin, training, and audit behavior. | D6: Confirm or revise: station staff, technician, station manager, operations manager, admin, government viewer, and support/auditor. | H6: Open
A7: ROL-02 | B7: Which stations may each role operate in? | C7: Authorization must enforce whether a person is station-bound or can work across locations. | D7: For each role, specify assigned station only, selected stations, all stations, or temporary manager-approved access. | H7: Open
A8: ROL-03 | B8: Who may create, edit, approve, export, and delete each record type? | C8: The system needs a practical permission matrix rather than a single admin flag. | D8: Cover riders, rentals, returns, payments, incidents, bike checks, maintenance, batteries, evidence, closeouts, conflicts, and reports. | H8: Open
A9: ROL-04 | B9: Who may perform a manual rental or return override? | C9: Overrides can change financial and vehicle state when normal controls fail. | D9: Specify permitted roles, required reason/evidence, offline behavior, and whether later manager approval is mandatory. | H9: Open
A10: ROL-05 | B10: Which actions require manager approval? | C10: High-risk actions should not be completed silently by ordinary staff. | D10: Consider payment corrections, missing-rental returns, inspection exceptions, conflict resolution, backup activation, and station reassignment. | H10: Open
A11: ROL-06 | B11: Which actions require two-person approval? | C11: Dual control may be required for high-value, safety-critical, or public-reporting changes. | D11: Consider refunds, payment deletion/correction, incident closure, clearing out-of-service, lost-bike recovery, and report publication. | H11: Open
A12: ROL-07 | B12: Who may clear maintenance-required or out-of-service status? | C12: Safety status must not be removed by an unauthorized user. | D12: Specify role, QC requirement, evidence, approval level, and emergency exception. | H12: Open
A13: ROL-08 | B13: Who may resolve tablet sync conflicts? | C13: Conflict actions can choose between offline staff records and newer canonical server state. | D13: Specify roles allowed to accept local, accept server, edit and accept, or reject local; require an audit note. | H13: Open
A14: ROL-09 | B14: What may the government viewer access? | C14: Government access should be useful and transparent but strictly read-only. | D14: List dashboards, record detail, audit history, exports, personal-data masking, station scope, and report publication status. | H14: Open
A15: ROL-10 | B15: How are staff accounts approved, suspended, and reviewed? | C15: Staff access must reflect current employment, station assignment, and training. | D15: Define account approver, onboarding prerequisites, periodic review, suspension triggers, offboarding time, and audit retention. | H15: Open

Sheet Backup & Reconciliation
A1: Backup mode and reconciliation
A2: Define when fallback operations begin and how temporary records safely enter the primary system.
A3: Affected work: Backup export and reconciliation | Complete the yellow response cells and update the response status.
A5: Question ID | B5: Decision Question | C5: Why This Decision Is Required | D5: Response Guidance / Examples | E5: Customer Response | F5: Decision Owner | G5: Target Response Date | H5: Response Status | I5: Notes / Follow-up
A6: BKP-01 | B6: Who may activate and end backup mode? | C6: Backup mode changes station procedure and must have a named accountable authority. | D6: Specify station manager, operations manager, admin, automatic triggers if any, and who confirms return to normal operation. | H6: Open
A7: BKP-02 | B7: Is backup mode station-specific or system-wide? | C7: The app and reports need to know whether unaffected stations continue normally. | D7: Choose station-specific, selected stations, or system-wide; describe escalation when an outage spreads. | H7: Open
A8: BKP-03 | B8: What is the official manual Rental ID format? | C8: A predictable business reference prevents collisions and supports staff communication and reconciliation. | D8: Approve or revise `YYYYMMDD-STATIONCODE-SEQUENCE`; provide station codes, sequence reset rules, and examples. | H8: Open
A9: BKP-04 | B9: What outage condition requires Google Workflow use? | C9: Staff need an objective transition point from local tablet queueing to the secondary fallback. | D9: Define duration, record-count, closeout, storage, sync-error, or manager-declaration triggers. | H9: Open
A10: BKP-05 | B10: Who owns the Google Forms, Sheet, and Drive folders? | C10: Operational ownership is needed for access, availability, retention, and support. | D10: Name the owning organization/account, administrators, backup owners, station editors, and support contact. | H10: Open
A11: BKP-06 | B11: Which Google Forms and fields are required? | C11: Fallback records must match primary fields closely enough to reconcile safely. | D11: Confirm Start Rental, Return Vehicle, Incident, Payment, Evidence, and Closeout forms; approve required fields and dropdown values. | H11: Open
A12: BKP-07 | B12: How quickly must backup records be reconciled? | C12: A deadline limits the period in which the temporary and canonical ledgers disagree. | D12: Choose same shift, same day, next morning, within 24 hours, or another SLA; define overdue escalation. | H12: Open
A13: BKP-08 | B13: Who reviews and approves imported backup records? | C13: Questionable manual data must be quarantined until an authorized manager decides what enters the canonical ledger. | D13: Specify primary reviewer, substitute, station scope, second approval cases, and review SLA. | H13: Open
A14: BKP-09 | B14: How are duplicate, missing, or conflicting records resolved? | C14: The reconciliation UI and SOP need agreed outcomes for predictable conflict types. | D14: Define treatment for duplicate IDs, start without return, return without start, bike already in use, missing actor/evidence, payment mismatch, and failed inspection. | H14: Open
A15: BKP-10 | B15: How long are backup files retained after reconciliation? | C15: Temporary Sheets, forms, exports, and evidence can contain personal and payment information. | D15: State retention, archive location, deletion authority, access review, and proof that canonical import succeeded. | H15: Open
A16: BKP-11 | B16: How will the backup process be tested? | C16: A documented fallback is not launch-ready until station staff can perform it under realistic outage conditions. | D16: Set drill frequency, participating stations, pass criteria, issue owner, evidence captured, and sign-off authority. | H16: Open

Sheet MVP Acceptance
A1: MVP acceptance and station demonstration
A2: Agree what must be demonstrated and signed off before station-assisted tablet rentals launch.
A3: Affected work: Release gate | Complete the yellow response cells and update the response status.
A5: Question ID | B5: Decision Question | C5: Why This Decision Is Required | D5: Response Guidance / Examples | E5: Customer Response | F5: Decision Owner | G5: Target Response Date | H5: Response Status | I5: Notes / Follow-up
A6: ACC-01 | B6: Who is authorized to accept the MVP? | C6: The project needs named business, operations, technical, safety, and customer representatives for final sign-off. | D6: List each approver, organization, role, decision scope, and substitute. | H6: Open
A7: ACC-02 | B7: What is the final acceptance date and review schedule? | C7: Teams need enough time for defect correction and re-testing before the public launch target. | D7: Confirm the target date, rehearsal date, formal review, defect-fix window, re-test date, and launch/no-launch meeting. | H7: Open
A8: ACC-03 | B8: Which launch stations and devices must pass? | C8: Acceptance should cover the real hardware and operating locations, not only a developer environment. | D8: Confirm all three locations, device count/models, network conditions, staff accounts, and representative fleet data. | H8: Open
A9: ACC-04 | B9: What customer registration scenario must be demonstrated? | C9: The demo should prove both app-assisted and station-assisted customer onboarding under approved PDPA rules. | D9: Specify local/tourist cases, no-mobile-app case, identity check, consent, bilingual content, and expected record evidence. | H9: Open
A10: ACC-05 | B10: What offline rental-start scenario must pass? | C10: This is the core service-continuity promise and a launch-critical path. | D10: Require Rental ID before release, rider/vehicle/staff/station data, passed inspection, payment reference, evidence, local bike block, and later exactly-once sync. | H10: Open
A11: ACC-06 | B11: What offline return and failed-inspection scenario must pass? | C11: The demo must prove that a returned unsafe bike cannot silently re-enter service. | D11: Require rental lookup/exception, return details, failed check, evidence, incident/maintenance record, local block, and canonical sync. | H11: Open
A12: ACC-07 | B12: What payment and evidence scenarios must pass? | C12: The system needs proof that financial and supporting records remain linked and reviewable through outages. | D12: Include pending manual slip, evidence upload after reconnect, rejected/mismatched payment, receipt/confirmation, and manager review. | H12: Open
A13: ACC-08 | B13: What synchronization and conflict scenarios must pass? | C13: The launch gate must show that retries and stale offline data do not corrupt the canonical ledger. | D13: Include replayed batch, replayed local ID, duplicate Rental ID, stale bike state, missing evidence, unauthorized station/device, and manager resolution. | H13: Open
A14: ACC-09 | B14: What backup workflow scenario must pass? | C14: A prolonged primary-system outage needs a tested secondary procedure and reconciliation path. | D14: Demonstrate backup activation, manual IDs, Google Forms/Sheet/Drive, export tracking, reconciliation, exception handling, and return to normal mode. | H14: Open
A15: ACC-10 | B15: What Daily Closeout scenario must pass? | C15: Shift handoff should expose unresolved rentals, payments, incidents, blocked bikes, and unsynced records. | D15: Define required counts, acknowledgement rules, manager exceptions, report/export output, and next-shift handoff. | H15: Open
A16: ACC-11 | B16: What performance and reliability thresholds apply? | C16: Acceptance needs measurable expectations beyond functional correctness. | D16: Specify screen response, sync duration/volume, supported offline duration, evidence upload limits, crash tolerance, battery impact, and recovery time. | H16: Open
A17: ACC-12 | B17: Which defects block launch? | C17: A shared severity rule prevents pressure to launch with unresolved safety, financial, privacy, or data-integrity defects. | D17: Define severity levels and no-go defects, accepted workarounds, waiver authority, documentation, and post-launch deadline. | H17: Open
... A19: ACC-14 | B19: What documents and evidence constitute final sign-off? | C19: The project needs an auditable acceptance package for customers and public stakeholders. | D19: List signed checklist, demo results, screenshots/video, test report, defect register, training record, SOP approval, data/privacy approval, and go-live authorization. | H19: Open
